Metadata-Version: 2.1
Name: odoo-addon-l10n_it_location_nuts
Version: 18.0.1.0.0.3
Requires-Python: >=3.10
Requires-Dist: odoo-addon-base_location_nuts==18.0.*
Requires-Dist: odoo==18.0.*
Summary: Opzioni NUTS specifiche per l'Italia
Home-page: https://github.com/OCA/l10n-italy
License: AGPL-3
Author: Agile Business Group, Odoo Community Association (OCA)
Author-email: support@odoo-community.org
Classifier: Programming Language :: Python
Classifier: Framework :: Odoo
Classifier: Framework :: Odoo :: 18.0
Classifier: License :: OSI Approved :: GNU Affero General Public License v3
